MANIFEST.in
setup.py
djangoplus/.DS_Store
djangoplus/.gitignore
djangoplus/LICENCE
djangoplus/README.md
djangoplus/__init__.py
djangoplus/requirements.txt
djangoplus.egg-info/PKG-INFO
djangoplus.egg-info/SOURCES.txt
djangoplus.egg-info/dependency_links.txt
djangoplus.egg-info/requires.txt
djangoplus.egg-info/top_level.txt
djangoplus/.idea/djangoplus.iml
djangoplus/.idea/modules.xml
djangoplus/.idea/vcs.xml
djangoplus/.idea/workspace.xml
djangoplus/.idea/inspectionProfiles/profiles_settings.xml
djangoplus/__pycache__/__init__.cpython-36.pyc
djangoplus/__pycache__/__init__.cpython-37.pyc
djangoplus/admin/.DS_Store
djangoplus/admin/__init__.py
djangoplus/admin/context_processors.py
djangoplus/admin/forms.py
djangoplus/admin/models.py
djangoplus/admin/tests.py
djangoplus/admin/urls.py
djangoplus/admin/views.py
djangoplus/admin/__pycache__/__init__.cpython-36.pyc
djangoplus/admin/__pycache__/__init__.cpython-37.pyc
djangoplus/admin/__pycache__/context_processors.cpython-36.pyc
djangoplus/admin/__pycache__/context_processors.cpython-37.pyc
djangoplus/admin/__pycache__/forms.cpython-36.pyc
djangoplus/admin/__pycache__/forms.cpython-37.pyc
djangoplus/admin/__pycache__/models.cpython-36.pyc
djangoplus/admin/__pycache__/models.cpython-37.pyc
djangoplus/admin/__pycache__/tests.cpython-37.pyc
djangoplus/admin/__pycache__/urls.cpython-36.pyc
djangoplus/admin/__pycache__/urls.cpython-37.pyc
djangoplus/admin/__pycache__/views.cpython-36.pyc
djangoplus/admin/__pycache__/views.cpython-37.pyc
djangoplus/admin/locale/pt_BR/LC_MESSAGES/django.mo
djangoplus/admin/locale/pt_BR/LC_MESSAGES/django.po
djangoplus/admin/management/__init__.py
djangoplus/admin/management/__pycache__/__init__.cpython-36.pyc
djangoplus/admin/management/__pycache__/__init__.cpython-37.pyc
djangoplus/admin/management/commands/__init__.py
djangoplus/admin/management/commands/backup.py
djangoplus/admin/management/commands/deploy.py
djangoplus/admin/management/commands/dump.py
djangoplus/admin/management/commands/migrate.py
djangoplus/admin/management/commands/migrate_to_postgres.py
djangoplus/admin/management/commands/pypi.py
djangoplus/admin/management/commands/reset_passwords.py
